{
    "AX": {
        "error": 2.9492972111664454e-07,
        "error_type": "SEM",
        "filter_outliers_dict": {
            "filter_outliers": false,
            "iterations": 0,
            "std_devs": 0,
            "use_iqr_filtering": false,
            "use_standard_deviation_filtering": false
        },
        "fit": "Average",
        "fn": 10,
        "include_baseline_error": false,
        "n": 10,
        "outlier_excluded": [],
        "reviewed": true,
        "user_excluded": [],
        "value": -1.5831924073950177e-07
    },
    "H1": {
        "error": 3.063773091091378e-07,
        "error_type": "SEM",
        "filter_outliers_dict": {
            "filter_outliers": false,
            "iterations": 0,
            "std_devs": 0,
            "use_iqr_filtering": false,
            "use_standard_deviation_filtering": false
        },
        "fit": "Average",
        "fn": 10,
        "include_baseline_error": false,
        "n": 10,
        "outlier_excluded": [],
        "reviewed": true,
        "user_excluded": [],
        "value": -9.557482735544909e-06
    },
    "H2": {
        "error": 5.136932432599452e-07,
        "error_type": "SEM",
        "filter_outliers_dict": {
            "filter_outliers": false,
            "iterations": 0,
            "std_devs": 0,
            "use_iqr_filtering": false,
            "use_standard_deviation_filtering": false
        },
        "fit": "Average",
        "fn": 10,
        "include_baseline_error": false,
        "n": 10,
        "outlier_excluded": [],
        "reviewed": true,
        "user_excluded": [],
        "value": -2.7417046396749357e-06
    },
    "L1": {
        "error": 2.8926522813748176e-07,
        "error_type": "SEM",
        "filter_outliers_dict": {
            "filter_outliers": false,
            "iterations": 0,
            "std_devs": 0,
            "use_iqr_filtering": false,
            "use_standard_deviation_filtering": false
        },
        "fit": "Average",
        "fn": 10,
        "include_baseline_error": false,
        "n": 10,
        "outlier_excluded": [],
        "reviewed": true,
        "user_excluded": [],
        "value": -3.563972548192851e-07
    },
    "L2": {
        "error": 0.04988876736063747,
        "error_type": "SEM",
        "filter_outliers_dict": {
            "filter_outliers": false,
            "iterations": 0,
            "std_devs": 0,
            "use_iqr_filtering": false,
            "use_standard_deviation_filtering": false
        },
        "fit": "Average",
        "fn": 10,
        "include_baseline_error": false,
        "n": 10,
        "outlier_excluded": [],
        "reviewed": true,
        "user_excluded": [],
        "value": 0.26000000908970833
    }
}