{
    "Ar36": {
        "error": 0.5005931608517004,
        "error_type": "",
        "fit": "previous",
        "references": [
            {
                "exclude": false,
                "record_id": "ba-01-N-3803"
            }
        ],
        "value": 17.508887163807785
    },
    "Ar37": {
        "error": 3.1542029580353395e-07,
        "error_type": "",
        "fit": "previous",
        "references": [
            {
                "exclude": false,
                "record_id": "ba-01-N-3803"
            }
        ],
        "value": 2.0717716515664355e-06
    },
    "Ar38": {
        "error": 3.9914465078814647e-07,
        "error_type": "",
        "fit": "previous",
        "references": [
            {
                "exclude": false,
                "record_id": "ba-01-N-3803"
            }
        ],
        "value": 9.813507299190527e-07
    },
    "Ar39": {
        "error": 3.2488665128464613e-07,
        "error_type": "",
        "fit": "previous",
        "references": [
            {
                "exclude": false,
                "record_id": "ba-01-N-3803"
            }
        ],
        "value": -7.544703810281107e-08
    },
    "Ar40": {
        "error": 1.0017422955852503e-06,
        "error_type": "",
        "fit": "previous",
        "references": [
            {
                "exclude": false,
                "record_id": "ba-01-N-3803"
            }
        ],
        "value": 5.046949233540196e-05
    }
}