{
    "Ar36": {
        "error": 1.9416824935585992,
        "error_type": "",
        "fit": "previous",
        "references": [
            {
                "exclude": false,
                "record_id": "bu-CC-N-2392"
            }
        ],
        "value": 440.5053462418326
    },
    "Ar37": {
        "error": 2.76502896528041e-07,
        "error_type": "",
        "fit": "previous",
        "references": [
            {
                "exclude": false,
                "record_id": "bu-CC-N-2392"
            }
        ],
        "value": 2.464082951249777e-06
    },
    "Ar38": {
        "error": 4.086557207563895e-07,
        "error_type": "",
        "fit": "previous",
        "references": [
            {
                "exclude": false,
                "record_id": "bu-CC-N-2392"
            }
        ],
        "value": 2.027517039475583e-06
    },
    "Ar39": {
        "error": 3.4058959644310514e-07,
        "error_type": "",
        "fit": "previous",
        "references": [
            {
                "exclude": false,
                "record_id": "bu-CC-N-2392"
            }
        ],
        "value": 2.4882883305223476e-07
    },
    "Ar40": {
        "error": 3.9049721832434494e-06,
        "error_type": "",
        "fit": "previous",
        "references": [
            {
                "exclude": false,
                "record_id": "bu-CC-N-2392"
            }
        ],
        "value": 0.002266354887049952
    }
}