{
    "Ar36": {
        "error": 1.9590350134421337,
        "error_type": "",
        "fit": "previous",
        "references": [
            {
                "exclude": false,
                "record_id": "bu-CC-N-2580"
            }
        ],
        "value": 396.6971056064521
    },
    "Ar37": {
        "error": 2.330514940937392e-07,
        "error_type": "",
        "fit": "previous",
        "references": [
            {
                "exclude": false,
                "record_id": "bu-CC-N-2580"
            }
        ],
        "value": 5.499189112219434e-06
    },
    "Ar38": {
        "error": 4.640222880818344e-07,
        "error_type": "",
        "fit": "previous",
        "references": [
            {
                "exclude": false,
                "record_id": "bu-CC-N-2580"
            }
        ],
        "value": 8.014627388505429e-07
    },
    "Ar39": {
        "error": 2.610870098263247e-07,
        "error_type": "",
        "fit": "previous",
        "references": [
            {
                "exclude": false,
                "record_id": "bu-CC-N-2580"
            }
        ],
        "value": 1.3699459177884774e-06
    },
    "Ar40": {
        "error": 2.322633586269974e-06,
        "error_type": "",
        "fit": "previous",
        "references": [
            {
                "exclude": false,
                "record_id": "bu-CC-N-2580"
            }
        ],
        "value": 0.0018108525583614675
    }
}