{
    "Ar36": {
        "error": 1.8612316284376633,
        "error_type": "",
        "fit": "previous",
        "references": [
            {
                "exclude": false,
                "record_id": "bu-CC-N-3095"
            }
        ],
        "value": 356.38005131937985
    },
    "Ar37": {
        "error": 3.0604288205949594e-07,
        "error_type": "",
        "fit": "previous",
        "references": [
            {
                "exclude": false,
                "record_id": "bu-CC-N-3095"
            }
        ],
        "value": 3.686324950837093e-06
    },
    "Ar38": {
        "error": 4.966446878916702e-07,
        "error_type": "",
        "fit": "previous",
        "references": [
            {
                "exclude": false,
                "record_id": "bu-CC-N-3095"
            }
        ],
        "value": 1.1556324670863437e-06
    },
    "Ar39": {
        "error": 3.076201651188187e-07,
        "error_type": "",
        "fit": "previous",
        "references": [
            {
                "exclude": false,
                "record_id": "bu-CC-N-3095"
            }
        ],
        "value": 1.7353011637395726e-06
    },
    "Ar40": {
        "error": 2.3622858198538623e-06,
        "error_type": "",
        "fit": "previous",
        "references": [
            {
                "exclude": false,
                "record_id": "bu-CC-N-3095"
            }
        ],
        "value": 0.001263842541092911
    }
}